stravawizard/__init__.py
stravawizard/utils.py
stravawizard/clients/__init__.py
stravawizard/clients/api_client/__init__.py
stravawizard/clients/api_client/strava_activity_api_client.py
stravawizard/clients/api_client/strava_api_client.py
stravawizard/clients/api_client/strava_athlete_api_client.py
stravawizard/clients/api_client/strava_base_api_client.py
stravawizard/clients/api_client/strava_request_handler.py
stravawizard/clients/oauth_client/__init__.py
stravawizard/clients/oauth_client/stravauth_base_client.py
stravawizard/clients/oauth_client/stravauth_client.py
stravawizard/clients/oauth_client/stravauth_credentials_manager.py
stravawizard/clients/oauth_client/stravauth_token_manager.py
stravawizard/tests/__init__.py
stravawizard/tests/test_stravauth_cli.py
stravawizard-2025.5.18.dist-info/licenses/LICENCE
stravawizard-2025.5.18.dist-info/METADATA
stravawizard-2025.5.18.dist-info/WHEEL
stravawizard-2025.5.18.dist-info/top_level.txt
stravawizard-2025.5.18.dist-info/RECORD
