Metadata-Version: 2.4
Name: stravawizard
Version: 2025.5.18
Summary: Python client library for interacting with Strava API - handles OAuth2 authentication and provides a simple interface to access Strava endpoints for athletes and activities
Author-email: KrazyMax <maxence.renaud@gmail.com>
License: MIT
Project-URL: Homepage, https://gitlab.com/KrazyMax/stravawizard
Project-URL: Repository, https://gitlab.com/KrazyMax/stravawizard.git
Project-URL: Issues, https://gitlab.com/KrazyMax/stravawizard/-/issues
Project-URL: Documentation, https://gitlab.com/KrazyMax/stravawizard/-/blob/main/README.md
Project-URL: Bug Tracker, https://gitlab.com/KrazyMax/stravawizard/-/issues
Keywords: strava,api,oauth2,oauth,athlete,activities,cycling,running,sports,fitness,authentication
Classifier: Development Status :: 5 - Production/Stable
Classifier: Intended Audience :: Developers
Classifier: License :: OSI Approved :: MIT License
Classifier: Programming Language :: Python :: 3
Classifier: Programming Language :: Python :: 3.11
Classifier: Programming Language :: Python :: 3.12
Classifier: Topic :: Software Development :: Libraries :: Python Modules
Classifier: Topic :: Internet :: WWW/HTTP
Classifier: Operating System :: OS Independent
Requires-Python: >=3.11
License-File: LICENCE
Requires-Dist: requests>=2.25.0
Provides-Extra: docs
Requires-Dist: mkdocs>=1.4.0; extra == "docs"
Requires-Dist: mkdocs-material>=9.0.0; extra == "docs"
Requires-Dist: mkdocstrings[python]>=0.20.0; extra == "docs"
Requires-Dist: mkdocs-gen-files>=0.5.0; extra == "docs"
Requires-Dist: mkdocs-git-revision-date-localized-plugin>=1.4.5; extra == "docs"
Dynamic: license-file
